django_solomon/__init__.py
django_solomon/admin.py
django_solomon/apps.py
django_solomon/backends.py
django_solomon/checks.py
django_solomon/config.py
django_solomon/forms.py
django_solomon/models.py
django_solomon/py.typed
django_solomon/urls.py
django_solomon/utilities.py
django_solomon/views.py
django_solomon/locale/de/LC_MESSAGES/django.po
django_solomon/locale/en/LC_MESSAGES/django.po
django_solomon/management/__init__.py
django_solomon/management/commands/__init__.py
django_solomon/migrations/0001_initial.py
django_solomon/migrations/__init__.py
django_solomon/templates/django_solomon/base/invalid_magic_link.html
django_solomon/templates/django_solomon/base/login_form.html
django_solomon/templates/django_solomon/base/magic_link_sent.html
django_solomon/templates/django_solomon/email/magic_link.mjml
django_solomon/templates/django_solomon/email/magic_link.txt
django_solomon-0.5.0.dist-info/METADATA
django_solomon-0.5.0.dist-info/WHEEL
django_solomon-0.5.0.dist-info/licenses/LICENSE
django_solomon-0.5.0.dist-info/RECORD
