Metadata-Version: 2.4
Name: django-solomon
Version: 0.5.0
Summary: A Django app for passwordless authentication using magic links.
Project-URL: Home, https://django-solomon.rtfd.io/
Project-URL: Documentation, https://django-solomon.rtfd.io/
Project-URL: Repository, https://codeberg.org/oliverandrich/django-solomon
Project-URL: Issue Tracker, https://codeberg.org/oliverandrich/django-solomon/issues
Author-email: Oliver Andrich <oliver@andrich.me>
License: MIT License
License-File: LICENSE
Keywords: django
Classifier: Development Status :: 4 - Beta
Classifier: Environment :: Web Environment
Classifier: Framework :: Django :: 4.2
Classifier: Framework :: Django :: 5.0
Classifier: Framework :: Django :: 5.1
Classifier: Framework :: Django :: 5.2
Classifier: Intended Audience :: Developers
Classifier: License :: OSI Approved :: MIT License
Classifier: Operating System :: OS Independent
Classifier: Programming Language :: Python :: 3.10
Classifier: Programming Language :: Python :: 3.11
Classifier: Programming Language :: Python :: 3.12
Classifier: Programming Language :: Python :: 3.13
Classifier: Topic :: Software Development :: Libraries
Classifier: Topic :: Utilities
Requires-Python: >=3.10
Requires-Dist: django>=4.2
Requires-Dist: mjml-python>=1.3.5
